MANIFEST.in
requirements.txt
setup.py
rqalpha_mod_ctp/VERSION.txt
rqalpha_mod_ctp/__init__.py
rqalpha_mod_ctp/__init__.pyc
rqalpha_mod_ctp/ctp_broker.py
rqalpha_mod_ctp/ctp_broker.pyc
rqalpha_mod_ctp/ctp_data_source.py
rqalpha_mod_ctp/ctp_data_source.pyc
rqalpha_mod_ctp/ctp_event_source.py
rqalpha_mod_ctp/ctp_event_source.pyc
rqalpha_mod_ctp/ctp_price_board.py
rqalpha_mod_ctp/ctp_price_board.pyc
rqalpha_mod_ctp/mod.py
rqalpha_mod_ctp/mod.pyc
rqalpha_mod_ctp/utils.py
rqalpha_mod_ctp/utils.pyc
rqalpha_mod_ctp.egg-info/PKG-INFO
rqalpha_mod_ctp.egg-info/SOURCES.txt
rqalpha_mod_ctp.egg-info/dependency_links.txt
rqalpha_mod_ctp.egg-info/not-zip-safe
rqalpha_mod_ctp.egg-info/requires.txt
rqalpha_mod_ctp.egg-info/top_level.txt
rqalpha_mod_ctp/ctp/__init__.py
rqalpha_mod_ctp/ctp/__init__.pyc
rqalpha_mod_ctp/ctp/api.py
rqalpha_mod_ctp/ctp/api.pyc
rqalpha_mod_ctp/ctp/data_dict.py
rqalpha_mod_ctp/ctp/data_dict.pyc
rqalpha_mod_ctp/ctp/md_gateway.py
rqalpha_mod_ctp/ctp/md_gateway.pyc
rqalpha_mod_ctp/ctp/trade_gateway.py
rqalpha_mod_ctp/ctp/trade_gateway.pyc
rqalpha_mod_ctp/ctp/pyctp/__init__.py
rqalpha_mod_ctp/ctp/pyctp/__init__.pyc
rqalpha_mod_ctp/ctp/pyctp/linux64_27/ApiStruct.py
rqalpha_mod_ctp/ctp/pyctp/linux64_27/ApiStruct.pyc
rqalpha_mod_ctp/ctp/pyctp/linux64_27/_MdApi.so
rqalpha_mod_ctp/ctp/pyctp/linux64_27/_TraderApi.so
rqalpha_mod_ctp/ctp/pyctp/linux64_27/__init__.py
rqalpha_mod_ctp/ctp/pyctp/linux64_27/__init__.pyc
rqalpha_mod_ctp/ctp/pyctp/linux64_27/libthostmduserapi.so
rqalpha_mod_ctp/ctp/pyctp/linux64_27/libthosttraderapi.so
rqalpha_mod_ctp/ctp/pyctp/linux64_34/ApiStruct.py
rqalpha_mod_ctp/ctp/pyctp/linux64_34/_MdApi.cpython-34m.so
rqalpha_mod_ctp/ctp/pyctp/linux64_34/_TraderApi.cpython-34m.so
rqalpha_mod_ctp/ctp/pyctp/linux64_34/__init__.py
rqalpha_mod_ctp/ctp/pyctp/linux64_34/libthostmduserapi.so
rqalpha_mod_ctp/ctp/pyctp/linux64_34/libthosttraderapi.so
rqalpha_mod_ctp/ctp/pyctp/linux64_35/ApiStruct.py
rqalpha_mod_ctp/ctp/pyctp/linux64_35/_MdApi.cpython-35m-x86_64-linux-gnu.so
rqalpha_mod_ctp/ctp/pyctp/linux64_35/_TraderApi.cpython-35m-x86_64-linux-gnu.so
rqalpha_mod_ctp/ctp/pyctp/linux64_35/__init__.py
rqalpha_mod_ctp/ctp/pyctp/linux64_35/libthostmduserapi.so
