Metadata-Version: 1.1
Name: rqalpha-mod-ctp
Version: 0.1.4
Summary: A mod for RQAlpha to connect with CTP
Home-page: https://github.com/ricequant/rqalpha-mod-ctp
Author: ricequant
Author-email: public@ricequant.com
License: Apache License v2
Platform: UNKNOWN
Classifier: Programming Language :: Python
Classifier: Operating System :: Microsoft :: Windows
Classifier: Operating System :: Unix
Classifier: Programming Language :: Python :: 2.7
Classifier: Programming Language :: Python :: 3.4
Classifier: Programming Language :: Python :: 3.5
